setup.py
gene_disease_pubmed/__init__.py
gene_disease_pubmed/gene_disease_pubmed.py
gene_disease_pubmed.egg-info/PKG-INFO
gene_disease_pubmed.egg-info/SOURCES.txt
gene_disease_pubmed.egg-info/dependency_links.txt
gene_disease_pubmed.egg-info/entry_points.txt
gene_disease_pubmed.egg-info/requires.txt
gene_disease_pubmed.egg-info/top_level.txt