Metadata-Version: 1.0
Name: gene-disease-pubmed
Version: 0.0.1
Summary: PubMed abstract query post processor.
Home-page: https://git.lumc.nl/j.f.j.laros/gene-disease-pubmed/tree/master
Author: Jeroen F.J. Laros
Author-email: J.F.J.Laros@lumc.nl
License: MIT License
Platform: any
